<?xml version="1.0"?>
<Results version="1.0">
<ReportNode type="testrun">
<ReportNode type="Step">
<Data>
    <Name>General run error.</Name>
    <Description>The HPE Unified Functional Testing computer is locked or logged off.</Description>
    <StartTime>2019-03-12 17:17:51</StartTime>
    <Result>Failed</Result>
    <Extension>
      <IsPlainTextNodeName>True</IsPlainTextNodeName>
    </Extension>
  </Data>
</ReportNode>
<ReportNode type="Step">
<Data>
    <Name>Stop Run</Name>
    <Description>Run stopped by user.</Description>
    <StartTime>2019-03-12 17:17:51</StartTime>
    <Result>Information</Result>
    <Extension>
      <IconKey>cadc388fac5342fdbf103dbdce6f90ff</IconKey>
      <IsPlainTextNodeName>True</IsPlainTextNodeName>
    </Extension>
  </Data>
</ReportNode>
<Data>
    <Name>טאסט בעברית1</Name>
    <ToolName>HPE Unified Functional Testing</ToolName>
    <ToolVersion>14.1</ToolVersion>
    <Description />
    <StartTime>2019-03-12 17:17:51</StartTime>
    <Duration>0</Duration>
    <Result>Failed</Result>
    <InputParameters />
    <Extension>
      <IconKey>d01e047f09df414a8ff07de177951e87</IconKey>
      <IsPlainTextNodeName>True</IsPlainTextNodeName>
    </Extension>
    <Environment>
      <Timezone>+02:00:00</Timezone>
      <Locale>English (United States)</Locale>
      <User>HPESWLAB\_alm_octane_auto</User>
      <CpuInfo>Intel(R) Xeon(R) CPU E5-2640 v3 @ 2.60GHz</CpuInfo>
      <NumberOfCores>4</NumberOfCores>
      <TotalMemory>8192</TotalMemory>
      <HostName>hpeswlab.net\MYD-VM08531</HostName>
      <OSInfo>Windows 7 Service Pack 1 (x64)</OSInfo>
    </Environment>
    <TestedApplications />
    <Links>
      <Link type="DataTable" reference="Default.xls" displayname="Default Data Table" />
    </Links>
  </Data>
</ReportNode>
<GeneralInfo>
    <ResultName>טאסט בעברית1</ResultName>
    <RunStartTime>2019-03-12 17:17:51</RunStartTime>
    <Timezone>+02:00:00</Timezone>
    <OrchestrationToolName>HPE Unified Functional Testing</OrchestrationToolName>
    <OrchestrationToolVersion>14.1</OrchestrationToolVersion>
  </GeneralInfo>
</Results>